p2d/__init__.py
p2d/__main__.py
p2d/_version.py
p2d/cli.py
p2d/contest.py
p2d/models.py
p2d/p2d.py
p2d/utils.py
p2d/testlib/LICENSE
p2d/testlib/testlib.h
p2d-0.4.0.dist-info/METADATA
p2d-0.4.0.dist-info/WHEEL
p2d-0.4.0.dist-info/entry_points.txt
p2d-0.4.0.dist-info/licenses/LICENSE
p2d-0.4.0.dist-info/RECORD
